{":CanvasComponent-master:entry:default@PreBuild":{"_inputs":[{"dataType":"ValueEntry","value":"{\"_name\":\"compileApiVersion\",\"_value\":22,\"_valueType\":\"number\"}"},{"dataType":"ValueEntry","value":"{\"_name\":\"compatibleApiVersion\",\"_value\":17,\"_valueType\":\"number\"}"},{"dataType":"ValueEntry","value":"{\"_name\":\"targetStatusCode\",\"_value\":2,\"_valueType\":\"number\"}"},{"dataType":"ValueEntry","value":"{\"_name\":\"apiType\",\"_value\":\"stageMode\",\"_valueType\":\"string\"}"},{"dataType":"ValueEntry","value":"{\"_name\":\"deviceType\",\"_value\":[\"phone\"],\"_valueType\":\"object\"}"},{"dataType":"ValueEntry","value":"{\"_name\":\"codeType\",\"_value\":true,\"_valueType\":\"boolean\"}"},{"dataType":"ValueEntry","value":"{\"_name\":\"sdkToolchainsComponentVersion\",\"_value\":\"6.0.2.130\",\"_valueType\":\"string\"}"},{"dataType":"ValueEntry","value":"{\"_name\":\"profileModuleName\",\"_value\":\"entry\",\"_valueType\":\"string\"}"},{"dataType":"ValueEntry","value":"{\"_name\":\"moduleJsonOpt\",\"_value\":\"{\\\"jsonFilePath\\\":\\\"D:\\\\\\\\CanvasComponent-master\\\\\\\\CanvasComponent-master\\\\\\\\entry\\\\\\\\src\\\\\\\\main\\\\\\\\module.json5\\\",\\\"profile\\\":{\\\"module\\\":{\\\"name\\\":\\\"entry\\\",\\\"type\\\":\\\"entry\\\",\\\"description\\\":\\\"$string:module_desc\\\",\\\"mainElement\\\":\\\"EntryAbility\\\",\\\"deviceTypes\\\":[\\\"phone\\\"],\\\"deliveryWithInstall\\\":true,\\\"installationFree\\\":false,\\\"pages\\\":\\\"$profile:main_pages\\\",\\\"abilities\\\":[{\\\"name\\\":\\\"EntryAbility\\\",\\\"srcEntry\\\":\\\"./ets/entryability/EntryAbility.ts\\\",\\\"description\\\":\\\"$string:EntryAbility_desc\\\",\\\"icon\\\":\\\"$media:icon\\\",\\\"label\\\":\\\"$string:EntryAbility_label\\\",\\\"startWindowIcon\\\":\\\"$media:icon\\\",\\\"startWindowBackground\\\":\\\"$color:start_window_background\\\",\\\"orientation\\\":\\\"portrait\\\",\\\"exported\\\":true,\\\"skills\\\":[{\\\"entities\\\":[\\\"entity.system.home\\\"],\\\"actions\\\":[\\\"action.system.home\\\"]}]}]}},\\\"deviceTypes\\\":[\\\"phone\\\"],\\\"deviceConfig\\\":\\\"deviceTypes\\\",\\\"configurationProfile\\\":\\\"module.json5\\\"}\",\"_valueType\":\"string\"}"},{"dataType":"ValueEntry","value":"{\"_name\":\"isSupportOhpmProj\",\"_value\":true,\"_valueType\":\"boolean\"}"},{"dataType":"ValueEntry","value":"{\"_name\":\"removePermissions\",\"_valueType\":\"undefined\"}"},{"dataType":"ValueEntry","value":"{\"_name\":\"isPreloadSystemSoEnabled\",\"_value\":false,\"_valueType\":\"boolean\"}"},{"dataType":"ValueEntry","value":"{\"_name\":\"isSingleFileEmitEnabled\",\"_value\":false,\"_valueType\":\"boolean\"}"},{"dataType":"ValueEntry","value":"{\"_name\":\"customTypes\",\"_value\":\"\",\"_valueType\":\"string\"}"},{"dataType":"ValueEntry","value":"{\"_name\":\"requiredDeviceType\",\"_value\":\"phone\",\"_valueType\":\"string\"}"},{"dataType":"ValueEntry","value":"{\"_name\":\"useNormalizedOHMUrl\",\"_value\":false,\"_valueType\":\"boolean\"}"},{"dataType":"ValueEntry","value":"{\"_name\":\"integrated_hsp\",\"_value\":false,\"_valueType\":\"boolean\"}"},{"dataType":"ValueEntry","value":"{\"_name\":\"sourceRoots\",\"_value\":true,\"_valueType\":\"boolean\"}"},{"dataType":"ValueEntry","value":"{\"_name\":\"transformLib\",\"_value\":\"\",\"_valueType\":\"string\"}"},{"dataType":"ValueEntry","value":"{\"_name\":\"byteCodeHar\",\"_value\":false,\"_valueType\":\"boolean\"}"},{"dataType":"ValueEntry","value":"{\"_name\":\"configuration\",\"_value\":\"\",\"_valueType\":\"string\"}"},{"dataType":"ValueEntry","value":"{\"_name\":\"configurationFileJson\",\"_value\":\"\",\"_valueType\":\"string\"}"},{"dataType":"ValueEntry","value":"{\"_name\":\"moduleDependencyNames\",\"_value\":[],\"_valueType\":\"object\"}"},{"dataType":"ValueEntry","value":"{\"_name\":\"isExpandImportEnabled\",\"_value\":false,\"_valueType\":\"boolean\"}"},{"dataType":"ValueEntry","value":"{\"_name\":\"excludeExpandImportDependencyNames\",\"_value\":[],\"_valueType\":\"object\"}"},{"dataType":"ValueEntry","value":"{\"_name\":\"BUILTIN_TASK_COMMAND\",\"_value\":\"\",\"_valueType\":\"string\"}"},{"dataType":"ValueEntry","value":"{\"_name\":\"BUILTIN_TASK_TOOLCHAIN\",\"_value\":\"\",\"_valueType\":\"string\"}"},{"dataType":"ValueEntry","value":"{\"_name\":\"BUILTIN_TASK_ENV\",\"_value\":\"\",\"_valueType\":\"string\"}"}],"_successful":true,"_projectName":"CanvasComponent-master","_moduleName":"entry","_taskName":"default@PreBuild","_key":":CanvasComponent-master:entry:default@PreBuild","_executionId":":CanvasComponent-master:entry:default@PreBuild:1776760994221","_inputFiles":{"dataType":"Map","value":[["D:\\CanvasComponent-master\\CanvasComponent-master\\AppScope\\app.json5",{"isDirectory":false,"fileSnapShotHashValue":"7969b46a3fd3bca7b52f47929472272dc92bceb4088c83e873dd47abc3ee0f81"}],["D:\\CanvasComponent-master\\CanvasComponent-master\\entry\\src\\main\\module.json5",{"isDirectory":false,"fileSnapShotHashValue":"02877489faf83d8b7219a40eeeddcd5bdc4ef1c0d902aec1f87b44c681223613"}],["D:\\CanvasComponent-master\\CanvasComponent-master\\build-profile.json5",{"fileSnapShotHashValue":"9d31cba1b960957eb03f3edbd1f5d25f17a6a3193ba7426774a7b879ba897955"}],["D:\\CanvasComponent-master\\CanvasComponent-master\\entry\\build-profile.json5",{"fileSnapShotHashValue":"53da7afe97d8956c4632345d102292b37a8a8220432246269ca0cb8e26745b9f"}],["D:\\CanvasComponent-master\\CanvasComponent-master\\entry\\src\\main\\resources\\base\\profile\\main_pages.json",{"fileSnapShotHashValue":"29c1810cae064728101e312e3b8cc88cf233b83920eb77f68108eae3261b276a"}],["D:\\CanvasComponent-master\\CanvasComponent-master\\hvigor\\hvigor-config.json5",{"isDirectory":true,"fileSnapShotHashValue":"a7bc08e03f503478bb504b9a5a906ffc0f52d471c3b392fb23b6502ae3aaf38e"}],["D:\\CanvasComponent-master\\CanvasComponent-master\\entry\\oh-package.json5",{"fileSnapShotHashValue":"51341dc9e67eda76e64209637ff2fa8b5232746c669ee572dcfe96f48f41be54"}],["D:\\CanvasComponent-master\\CanvasComponent-master\\oh-package.json5",{"fileSnapShotHashValue":"d54b49750dc46278cc05687d29d23b93067242e663c8256750c4932a3f3100c9"}]]},"_outputFiles":{"dataType":"Map","value":[]}},":CanvasComponent-master:entry:default@CreateModuleInfo":{"_inputs":[{"dataType":"ValueEntry","value":"{\"_name\":\"ohosUiTransformOptimization\",\"_value\":false,\"_valueType\":\"boolean\"}"},{"dataType":"ValueEntry","value":"{\"_name\":\"integratedHspUseGetCurrentBundleName\",\"_value\":false,\"_valueType\":\"boolean\"}"},{"dataType":"ValueEntry","value":"{\"_name\":\"BUILTIN_TASK_COMMAND\",\"_value\":\"\",\"_valueType\":\"string\"}"},{"dataType":"ValueEntry","value":"{\"_name\":\"BUILTIN_TASK_TOOLCHAIN\",\"_value\":\"\",\"_valueType\":\"string\"}"},{"dataType":"ValueEntry","value":"{\"_name\":\"BUILTIN_TASK_ENV\",\"_value\":\"\",\"_valueType\":\"string\"}"}],"_successful":false,"_projectName":"CanvasComponent-master","_moduleName":"entry","_taskName":"default@CreateModuleInfo","_key":":CanvasComponent-master:entry:default@CreateModuleInfo","_executionId":":CanvasComponent-master:entry:default@CreateModuleInfo:1776760994332","_inputFiles":{"dataType":"Map","value":[]},"_outputFiles":{"dataType":"Map","value":[["D:\\CanvasComponent-master\\CanvasComponent-master\\entry\\build\\default\\generated\\profile\\default\\ModuleInfo.ts",{"isDirectory":false,"fileSnapShotHashValue":""}]]}},":CanvasComponent-master:entry:default@GenerateMetadata":{"_inputs":[{"dataType":"ValueEntry","value":"{\"_name\":\"remoteHspMetaData\",\"_value\":\"\",\"_valueType\":\"string\"}"},{"dataType":"ValueEntry","value":"{\"_name\":\"artifactName\",\"_value\":\"\",\"_valueType\":\"string\"}"},{"dataType":"ValueEntry","value":"{\"_name\":\"relatedEntryModules\",\"_value\":\"\",\"_valueType\":\"string\"}"},{"dataType":"ValueEntry","value":"{\"_name\":\"targetDeviceType\",\"_value\":[\"phone\"],\"_valueType\":\"object\"}"},{"dataType":"ValueEntry","value":"{\"_name\":\"isSigned\",\"_value\":false,\"_valueType\":\"boolean\"}"},{"dataType":"ValueEntry","value":"{\"_name\":\"BUILTIN_TASK_COMMAND\",\"_value\":\"\",\"_valueType\":\"string\"}"},{"dataType":"ValueEntry","value":"{\"_name\":\"BUILTIN_TASK_TOOLCHAIN\",\"_value\":\"\",\"_valueType\":\"string\"}"},{"dataType":"ValueEntry","value":"{\"_name\":\"BUILTIN_TASK_ENV\",\"_value\":\"\",\"_valueType\":\"string\"}"}],"_successful":true,"_projectName":"CanvasComponent-master","_moduleName":"entry","_taskName":"default@GenerateMetadata","_key":":CanvasComponent-master:entry:default@GenerateMetadata","_executionId":":CanvasComponent-master:entry:default@GenerateMetadata:1776760994334","_inputFiles":{"dataType":"Map","value":[["D:\\CanvasComponent-master\\CanvasComponent-master\\entry\\src\\main\\module.json5",{"fileSnapShotHashValue":"02877489faf83d8b7219a40eeeddcd5bdc4ef1c0d902aec1f87b44c681223613"}]]},"_outputFiles":{"dataType":"Map","value":[["D:\\CanvasComponent-master\\CanvasComponent-master\\entry\\build\\default\\intermediates\\hap_metadata\\default\\output_metadata.json",{"fileSnapShotHashValue":"249023676d73bd90ecb21778fb18c273dabe7a1633b871015919e1ea956ee1c2"}]]}},":CanvasComponent-master:entry:default@MergeProfile":{"_inputs":[{"dataType":"ValueEntry","value":"{\"_name\":\"targetSdkVersion\",\"_value\":22,\"_valueType\":\"number\"}"},{"dataType":"ValueEntry","value":"{\"_name\":\"compatibleSdkVersion\",\"_value\":17,\"_valueType\":\"number\"}"},{"dataType":"ValueEntry","value":"{\"_name\":\"releaseType\",\"_value\":\"Release\",\"_valueType\":\"string\"}"},{"dataType":"ValueEntry","value":"{\"_name\":\"buildRoot\",\"_value\":\"build\",\"_valueType\":\"string\"}"},{"dataType":"ValueEntry","value":"{\"_name\":\"isDebug\",\"_value\":true,\"_valueType\":\"boolean\"}"},{"dataType":"ValueEntry","value":"{\"_name\":\"asanEnable\",\"_value\":false,\"_valueType\":\"boolean\"}"},{"dataType":"ValueEntry","value":"{\"_name\":\"tsanEnable\",\"_value\":false,\"_valueType\":\"boolean\"}"},{"dataType":"ValueEntry","value":"{\"_name\":\"hwasanEnable\",\"_value\":false,\"_valueType\":\"boolean\"}"},{"dataType":"ValueEntry","value":"{\"_name\":\"ubsanEnable\",\"_value\":false,\"_valueType\":\"boolean\"}"},{"dataType":"ValueEntry","value":"{\"_name\":\"moduleJsonOpt\",\"_value\":\"{\\\"module\\\":{\\\"name\\\":\\\"entry\\\",\\\"type\\\":\\\"entry\\\",\\\"description\\\":\\\"$string:module_desc\\\",\\\"mainElement\\\":\\\"EntryAbility\\\",\\\"deviceTypes\\\":[\\\"phone\\\"],\\\"deliveryWithInstall\\\":true,\\\"installationFree\\\":false,\\\"pages\\\":\\\"$profile:main_pages\\\",\\\"abilities\\\":[{\\\"name\\\":\\\"EntryAbility\\\",\\\"srcEntry\\\":\\\"./ets/entryability/EntryAbility.ts\\\",\\\"description\\\":\\\"$string:EntryAbility_desc\\\",\\\"icon\\\":\\\"$media:icon\\\",\\\"label\\\":\\\"$string:EntryAbility_label\\\",\\\"startWindowIcon\\\":\\\"$media:icon\\\",\\\"startWindowBackground\\\":\\\"$color:start_window_background\\\",\\\"orientation\\\":\\\"portrait\\\",\\\"exported\\\":true,\\\"skills\\\":[{\\\"entities\\\":[\\\"entity.system.home\\\"],\\\"actions\\\":[\\\"action.system.home\\\"]}]}]}}\",\"_valueType\":\"string\"}"},{"dataType":"ValueEntry","value":"{\"_name\":\"isHarModule\",\"_value\":false,\"_valueType\":\"boolean\"}"},{"dataType":"ValueEntry","value":"{\"_name\":\"multiProjects\",\"_value\":false,\"_valueType\":\"boolean\"}"},{"dataType":"ValueEntry","value":"{\"_name\":\"buildProfileAbilities\",\"_valueType\":\"undefined\"}"},{"dataType":"ValueEntry","value":"{\"_name\":\"projectConfigAppOpt\",\"_valueType\":\"undefined\"}"},{"dataType":"ValueEntry","value":"{\"_name\":\"appJsonOpt\",\"_value\":\"{\\\"app\\\":{\\\"bundleName\\\":\\\"com.example.canvascomponent\\\",\\\"vendor\\\":\\\"example\\\",\\\"versionCode\\\":1000000,\\\"versionName\\\":\\\"1.0.0\\\",\\\"icon\\\":\\\"$media:app_icon\\\",\\\"label\\\":\\\"$string:app_name\\\"}}\",\"_valueType\":\"string\"}"},{"dataType":"ValueEntry","value":"{\"_name\":\"integratedHsp\",\"_value\":false,\"_valueType\":\"boolean\"}"},{"dataType":"ValueEntry","value":"{\"_name\":\"removePermissions\",\"_valueType\":\"undefined\"}"},{"dataType":"ValueEntry","value":"{\"_name\":\"isBundledDependencies\",\"_value\":false,\"_valueType\":\"boolean\"}"},{"dataType":"ValueEntry","value":"{\"_name\":\"packageName\",\"_value\":\"entry\",\"_valueType\":\"string\"}"},{"dataType":"ValueEntry","value":"{\"_name\":\"ohLibs\",\"_value\":[],\"_valueType\":\"object\"}"},{"dataType":"ValueEntry","value":"{\"_name\":\"includeAppScopeRes\",\"_value\":\"\",\"_valueType\":\"string\"}"},{"dataType":"ValueEntry","value":"{\"_name\":\"BUILTIN_TASK_COMMAND\",\"_value\":\"\",\"_valueType\":\"string\"}"},{"dataType":"ValueEntry","value":"{\"_name\":\"BUILTIN_TASK_TOOLCHAIN\",\"_value\":\"\",\"_valueType\":\"string\"}"},{"dataType":"ValueEntry","value":"{\"_name\":\"BUILTIN_TASK_ENV\",\"_value\":\"\",\"_valueType\":\"string\"}"}],"_successful":true,"_projectName":"CanvasComponent-master","_moduleName":"entry","_taskName":"default@MergeProfile","_key":":CanvasComponent-master:entry:default@MergeProfile","_executionId":":CanvasComponent-master:entry:default@MergeProfile:1776760994341","_inputFiles":{"dataType":"Map","value":[["D:\\CanvasComponent-master\\CanvasComponent-master\\AppScope\\app.json5",{"fileSnapShotHashValue":"7969b46a3fd3bca7b52f47929472272dc92bceb4088c83e873dd47abc3ee0f81"}],["D:\\CanvasComponent-master\\CanvasComponent-master\\build-profile.json5",{"fileSnapShotHashValue":"9d31cba1b960957eb03f3edbd1f5d25f17a6a3193ba7426774a7b879ba897955"}],["D:\\CanvasComponent-master\\CanvasComponent-master\\entry\\src\\main\\module.json5",{"fileSnapShotHashValue":"02877489faf83d8b7219a40eeeddcd5bdc4ef1c0d902aec1f87b44c681223613"}]]},"_outputFiles":{"dataType":"Map","value":[["D:\\CanvasComponent-master\\CanvasComponent-master\\entry\\build\\default\\intermediates\\merge_profile\\default\\module.json",{"fileSnapShotHashValue":"16354ac41505943529c02355676d9a726f0c49ad60e33265033bfff8e16ebb85"}]]}},":CanvasComponent-master:entry:default@CreateBuildProfile":{"_inputs":[{"dataType":"ValueEntry","value":"{\"_name\":\"buildMode\",\"_value\":\"Debug\",\"_valueType\":\"string\"}"},{"dataType":"ValueEntry","value":"{\"_name\":\"buildModeName\",\"_value\":\"debug\",\"_valueType\":\"string\"}"},{"dataType":"ValueEntry","value":"{\"_name\":\"buildProfileFields\",\"_value\":\"\",\"_valueType\":\"string\"}"},{"dataType":"ValueEntry","value":"{\"_name\":\"projectOhosConfigAppOpt\",\"_value\":\"\",\"_valueType\":\"string\"}"},{"dataType":"ValueEntry","value":"{\"_name\":\"BUILTIN_TASK_COMMAND\",\"_value\":\"\",\"_valueType\":\"string\"}"},{"dataType":"ValueEntry","value":"{\"_name\":\"BUILTIN_TASK_TOOLCHAIN\",\"_value\":\"\",\"_valueType\":\"string\"}"},{"dataType":"ValueEntry","value":"{\"_name\":\"BUILTIN_TASK_ENV\",\"_value\":\"\",\"_valueType\":\"string\"}"}],"_successful":true,"_projectName":"CanvasComponent-master","_moduleName":"entry","_taskName":"default@CreateBuildProfile","_key":":CanvasComponent-master:entry:default@CreateBuildProfile","_executionId":":CanvasComponent-master:entry:default@CreateBuildProfile:1776760994346","_inputFiles":{"dataType":"Map","value":[["D:\\CanvasComponent-master\\CanvasComponent-master\\AppScope\\app.json5",{"fileSnapShotHashValue":"7969b46a3fd3bca7b52f47929472272dc92bceb4088c83e873dd47abc3ee0f81"}],["D:\\CanvasComponent-master\\CanvasComponent-master\\build-profile.json5",{"fileSnapShotHashValue":"9d31cba1b960957eb03f3edbd1f5d25f17a6a3193ba7426774a7b879ba897955"}]]},"_outputFiles":{"dataType":"Map","value":[["D:\\CanvasComponent-master\\CanvasComponent-master\\entry\\build\\default\\generated\\profile\\default\\BuildProfile.ets",{"fileSnapShotHashValue":"acf4793b117a82f865112500fa5a2ea62987ab6caee7e85d030b5af044ff7cb3"}]]}},":CanvasComponent-master:entry:default@GeneratePkgContextInfo":{"_inputs":[{"dataType":"ValueEntry","value":"{\"_name\":\"pkgContextInfoMap\",\"_value\":\"{\\\"entry\\\":{\\\"packageName\\\":\\\"entry\\\",\\\"bundleName\\\":\\\"\\\",\\\"moduleName\\\":\\\"\\\",\\\"version\\\":\\\"\\\",\\\"entryPath\\\":\\\"src/main/\\\",\\\"isSO\\\":false,\\\"dependencyAlias\\\":\\\"\\\"}}\",\"_valueType\":\"string\"}"},{"dataType":"ValueEntry","value":"{\"_name\":\"useNormalizedOHMUrl\",\"_value\":false,\"_valueType\":\"boolean\"}"},{"dataType":"ValueEntry","value":"{\"_name\":\"BUILTIN_TASK_COMMAND\",\"_value\":\"\",\"_valueType\":\"string\"}"},{"dataType":"ValueEntry","value":"{\"_name\":\"BUILTIN_TASK_TOOLCHAIN\",\"_value\":\"\",\"_valueType\":\"string\"}"},{"dataType":"ValueEntry","value":"{\"_name\":\"BUILTIN_TASK_ENV\",\"_value\":\"\",\"_valueType\":\"string\"}"}],"_successful":false,"_projectName":"CanvasComponent-master","_moduleName":"entry","_taskName":"default@GeneratePkgContextInfo","_key":":CanvasComponent-master:entry:default@GeneratePkgContextInfo","_executionId":":CanvasComponent-master:entry:default@GeneratePkgContextInfo:1776760994361","_inputFiles":{"dataType":"Map","value":[]},"_outputFiles":{"dataType":"Map","value":[["D:\\CanvasComponent-master\\CanvasComponent-master\\entry\\build\\default\\intermediates\\loader\\default\\pkgContextInfo.json",{"isDirectory":false,"fileSnapShotHashValue":""}]]}},":CanvasComponent-master:entry:default@ProcessIntegratedHsp":{"_inputs":[{"dataType":"ValueEntry","value":"{\"_name\":\"bundleName\",\"_value\":\"com.example.canvascomponent\",\"_valueType\":\"string\"}"},{"dataType":"ValueEntry","value":"{\"_name\":\"versionCode\",\"_value\":1000000,\"_valueType\":\"number\"}"},{"dataType":"ValueEntry","value":"{\"_name\":\"BUILTIN_TASK_COMMAND\",\"_value\":\"\",\"_valueType\":\"string\"}"},{"dataType":"ValueEntry","value":"{\"_name\":\"BUILTIN_TASK_TOOLCHAIN\",\"_value\":\"\",\"_valueType\":\"string\"}"},{"dataType":"ValueEntry","value":"{\"_name\":\"BUILTIN_TASK_ENV\",\"_value\":\"\",\"_valueType\":\"string\"}"}],"_successful":true,"_projectName":"CanvasComponent-master","_moduleName":"entry","_taskName":"default@ProcessIntegratedHsp","_key":":CanvasComponent-master:entry:default@ProcessIntegratedHsp","_executionId":":CanvasComponent-master:entry:default@ProcessIntegratedHsp:1776760994367","_inputFiles":{"dataType":"Map","value":[]},"_outputFiles":{"dataType":"Map","value":[["D:\\CanvasComponent-master\\CanvasComponent-master\\build\\cache\\default\\integrated_hsp\\integratedHspCache.json",{"isDirectory":false,"fileSnapShotHashValue":""}]]}},":CanvasComponent-master:entry:default@MakePackInfo":{"_inputs":[{"dataType":"ValueEntry","value":"{\"_name\":\"deviceTypes\",\"_value\":[\"phone\"],\"_valueType\":\"object\"}"},{"dataType":"ValueEntry","value":"{\"_name\":\"compileSdkVersion\",\"_value\":22,\"_valueType\":\"number\"}"},{"dataType":"ValueEntry","value":"{\"_name\":\"compatibleSdkVersion\",\"_value\":17,\"_valueType\":\"number\"}"},{"dataType":"ValueEntry","value":"{\"_name\":\"moduleJsonOpt\",\"_value\":\"{\\\"module\\\":{\\\"name\\\":\\\"entry\\\",\\\"type\\\":\\\"entry\\\",\\\"description\\\":\\\"$string:module_desc\\\",\\\"mainElement\\\":\\\"EntryAbility\\\",\\\"deviceTypes\\\":[\\\"phone\\\"],\\\"deliveryWithInstall\\\":true,\\\"pages\\\":\\\"$profile:main_pages\\\",\\\"abilities\\\":[{\\\"name\\\":\\\"EntryAbility\\\",\\\"srcEntry\\\":\\\"./ets/entryability/EntryAbility.ts\\\",\\\"description\\\":\\\"$string:EntryAbility_desc\\\",\\\"icon\\\":\\\"$media:icon\\\",\\\"label\\\":\\\"$string:EntryAbility_label\\\",\\\"startWindowIcon\\\":\\\"$media:icon\\\",\\\"startWindowBackground\\\":\\\"$color:start_window_background\\\",\\\"orientation\\\":\\\"portrait\\\",\\\"exported\\\":true,\\\"skills\\\":[{\\\"entities\\\":[\\\"entity.system.home\\\"],\\\"actions\\\":[\\\"action.system.home\\\"]}]}]}}\",\"_valueType\":\"string\"}"},{"dataType":"ValueEntry","value":"{\"_name\":\"releaseType\",\"_value\":\"Release\",\"_valueType\":\"string\"}"},{"dataType":"ValueEntry","value":"{\"_name\":\"projectConfigAppOpt\",\"_valueType\":\"undefined\"}"},{"dataType":"ValueEntry","value":"{\"_name\":\"integratedHsp\",\"_value\":false,\"_valueType\":\"boolean\"}"},{"dataType":"ValueEntry","value":"{\"_name\":\"appResOpt\",\"_value\":\"{\\\"app\\\":{\\\"bundleName\\\":\\\"com.example.canvascomponent\\\",\\\"vendor\\\":\\\"example\\\",\\\"versionCode\\\":1000000,\\\"versionName\\\":\\\"1.0.0\\\",\\\"icon\\\":\\\"$media:app_icon\\\",\\\"label\\\":\\\"$string:app_name\\\"}}\",\"_valueType\":\"string\"}"},{"dataType":"ValueEntry","value":"{\"_name\":\"BUILTIN_TASK_COMMAND\",\"_value\":\"\",\"_valueType\":\"string\"}"},{"dataType":"ValueEntry","value":"{\"_name\":\"BUILTIN_TASK_TOOLCHAIN\",\"_value\":\"\",\"_valueType\":\"string\"}"},{"dataType":"ValueEntry","value":"{\"_name\":\"BUILTIN_TASK_ENV\",\"_value\":\"\",\"_valueType\":\"string\"}"}],"_successful":true,"_projectName":"CanvasComponent-master","_moduleName":"entry","_taskName":"default@MakePackInfo","_key":":CanvasComponent-master:entry:default@MakePackInfo","_executionId":":CanvasComponent-master:entry:default@MakePackInfo:1776760994372","_inputFiles":{"dataType":"Map","value":[["D:\\CanvasComponent-master\\CanvasComponent-master\\AppScope\\app.json5",{"fileSnapShotHashValue":"7969b46a3fd3bca7b52f47929472272dc92bceb4088c83e873dd47abc3ee0f81"}],["D:\\CanvasComponent-master\\CanvasComponent-master\\entry\\src\\main\\module.json5",{"fileSnapShotHashValue":"02877489faf83d8b7219a40eeeddcd5bdc4ef1c0d902aec1f87b44c681223613"}],["D:\\CanvasComponent-master\\CanvasComponent-master\\build-profile.json5",{"fileSnapShotHashValue":"9d31cba1b960957eb03f3edbd1f5d25f17a6a3193ba7426774a7b879ba897955"}]]},"_outputFiles":{"dataType":"Map","value":[["D:\\CanvasComponent-master\\CanvasComponent-master\\entry\\build\\default\\outputs\\default\\pack.info",{"fileSnapShotHashValue":"779ad8a14a2cae4ec2a1276a51b649e9b5a39772ef3a30d095099d8f41fe00f2"}]]}},":CanvasComponent-master:entry:default@SyscapTransform":{"_inputs":[{"dataType":"ValueEntry","value":"{\"_name\":\"deviceTypes\",\"_value\":[\"phone\"],\"_valueType\":\"object\"}"},{"dataType":"ValueEntry","value":"{\"_name\":\"BUILTIN_TASK_COMMAND\",\"_value\":\"\",\"_valueType\":\"string\"}"},{"dataType":"ValueEntry","value":"{\"_name\":\"BUILTIN_TASK_TOOLCHAIN\",\"_value\":\"\",\"_valueType\":\"string\"}"},{"dataType":"ValueEntry","value":"{\"_name\":\"BUILTIN_TASK_ENV\",\"_value\":\"\",\"_valueType\":\"string\"}"}],"_successful":true,"_projectName":"CanvasComponent-master","_moduleName":"entry","_taskName":"default@SyscapTransform","_key":":CanvasComponent-master:entry:default@SyscapTransform","_executionId":":CanvasComponent-master:entry:default@SyscapTransform:1776760994378","_inputFiles":{"dataType":"Map","value":[["D:\\DevEco Studio\\sdk\\default\\openharmony\\toolchains\\syscap_tool.exe",{"fileSnapShotHashValue":"995d66db4b4b2e82070083b451ccad676be876e3d31a36cbe20aae524868f06c"}],["D:\\DevEco Studio\\sdk\\default\\openharmony\\ets\\api\\device-define",{"fileSnapShotHashValue":"6f1046d13d0fb23e7fd03f8ccbe062910954f9321e4ab39c4bb6bc89a5bb0dfd"}]]},"_outputFiles":{"dataType":"Map","value":[["D:\\CanvasComponent-master\\CanvasComponent-master\\entry\\build\\default\\intermediates\\syscap\\default\\rpcid.sc",{"fileSnapShotHashValue":""}]]}},":CanvasComponent-master:entry:default@ProcessProfile":{"_inputs":[{"dataType":"ValueEntry","value":"{\"_name\":\"arkEnable\",\"_value\":true,\"_valueType\":\"boolean\"}"},{"dataType":"ValueEntry","value":"{\"_name\":\"compileMode\",\"_value\":\"esmodule\",\"_valueType\":\"string\"}"},{"dataType":"ValueEntry","value":"{\"_name\":\"deviceTypes\",\"_value\":[\"phone\"],\"_valueType\":\"object\"}"},{"dataType":"ValueEntry","value":"{\"_name\":\"dependency\",\"_value\":\"[]\",\"_valueType\":\"string\"}"},{"dataType":"ValueEntry","value":"{\"_name\":\"harExcludeHSPDependencies\",\"_valueType\":\"undefined\"}"},{"dataType":"ValueEntry","value":"{\"_name\":\"compatibleSdkVersionStage\",\"_value\":\"\",\"_valueType\":\"string\"}"},{"dataType":"ValueEntry","value":"{\"_name\":\"isFakeUIAbilityExists\",\"_value\":false,\"_valueType\":\"boolean\"}"},{"dataType":"ValueEntry","value":"{\"_name\":\"BUILTIN_TASK_COMMAND\",\"_value\":\"\",\"_valueType\":\"string\"}"},{"dataType":"ValueEntry","value":"{\"_name\":\"BUILTIN_TASK_TOOLCHAIN\",\"_value\":\"\",\"_valueType\":\"string\"}"},{"dataType":"ValueEntry","value":"{\"_name\":\"BUILTIN_TASK_ENV\",\"_value\":\"\",\"_valueType\":\"string\"}"}],"_successful":true,"_projectName":"CanvasComponent-master","_moduleName":"entry","_taskName":"default@ProcessProfile","_key":":CanvasComponent-master:entry:default@ProcessProfile","_executionId":":CanvasComponent-master:entry:default@ProcessProfile:1776760994382","_inputFiles":{"dataType":"Map","value":[["D:\\CanvasComponent-master\\CanvasComponent-master\\entry\\build\\default\\intermediates\\merge_profile\\default\\module.json",{"fileSnapShotHashValue":"16354ac41505943529c02355676d9a726f0c49ad60e33265033bfff8e16ebb85"}]]},"_outputFiles":{"dataType":"Map","value":[["D:\\CanvasComponent-master\\CanvasComponent-master\\entry\\build\\default\\intermediates\\process_profile\\default\\module.json",{"fileSnapShotHashValue":"a7bab3715ca865badc3a3b67b45176eb69f8792b9a6d489187c27282ea9816d9"}]]}},":CanvasComponent-master:entry:default@ProcessRouterMap":{"_inputs":[{"dataType":"ValueEntry","value":"{\"_name\":\"useNormalizedOHMUrl\",\"_value\":false,\"_valueType\":\"boolean\"}"},{"dataType":"ValueEntry","value":"{\"_name\":\"obfuscated\",\"_value\":true,\"_valueType\":\"boolean\"}"},{"dataType":"ValueEntry","value":"{\"_name\":\"byteCodeHar\",\"_value\":false,\"_valueType\":\"boolean\"}"},{"dataType":"ValueEntry","value":"{\"_name\":\"bundleName\",\"_value\":\"com.example.canvascomponent\",\"_valueType\":\"string\"}"},{"dataType":"ValueEntry","value":"{\"_name\":\"moduleName\",\"_value\":\"entry\",\"_valueType\":\"string\"}"},{"dataType":"ValueEntry","value":"{\"_name\":\"harPackageNameList\",\"_value\":\"[]\",\"_valueType\":\"string\"}"},{"dataType":"ValueEntry","value":"{\"_name\":\"localDependencyRouterMapObjArray\",\"_value\":\"4f53cda18c2baa0c0354bb5f9a3ecbe5ed12ab4d8e11ba873c2f11161202b945\",\"_valueType\":\"string\"}"},{"dataType":"ValueEntry","value":"{\"_name\":\"remoteDependencyRouterMapObjArray\",\"_value\":\"4f53cda18c2baa0c0354bb5f9a3ecbe5ed12ab4d8e11ba873c2f11161202b945\",\"_valueType\":\"string\"}"},{"dataType":"ValueEntry","value":"{\"_name\":\"BUILTIN_TASK_COMMAND\",\"_value\":\"\",\"_valueType\":\"string\"}"},{"dataType":"ValueEntry","value":"{\"_name\":\"BUILTIN_TASK_TOOLCHAIN\",\"_value\":\"\",\"_valueType\":\"string\"}"},{"dataType":"ValueEntry","value":"{\"_name\":\"BUILTIN_TASK_ENV\",\"_value\":\"\",\"_valueType\":\"string\"}"}],"_successful":true,"_projectName":"CanvasComponent-master","_moduleName":"entry","_taskName":"default@ProcessRouterMap","_key":":CanvasComponent-master:entry:default@ProcessRouterMap","_executionId":":CanvasComponent-master:entry:default@ProcessRouterMap:1776760995705","_inputFiles":{"dataType":"Map","value":[["D:\\CanvasComponent-master\\CanvasComponent-master\\entry\\oh-package.json5",{"fileSnapShotHashValue":"51341dc9e67eda76e64209637ff2fa8b5232746c669ee572dcfe96f48f41be54"}],["D:\\CanvasComponent-master\\CanvasComponent-master\\oh-package.json5",{"fileSnapShotHashValue":"d54b49750dc46278cc05687d29d23b93067242e663c8256750c4932a3f3100c9"}],["D:\\CanvasComponent-master\\CanvasComponent-master\\entry\\src\\main\\module.json5",{"fileSnapShotHashValue":"02877489faf83d8b7219a40eeeddcd5bdc4ef1c0d902aec1f87b44c681223613"}]]},"_outputFiles":{"dataType":"Map","value":[["D:\\CanvasComponent-master\\CanvasComponent-master\\entry\\build\\default\\intermediates\\router_map\\default\\temp-router-map.json",{"fileSnapShotHashValue":"cb870ddb3078e4decce779a4945ca28e92b0187c5dae928b3021ce5a15d60cf8"}],["D:\\CanvasComponent-master\\CanvasComponent-master\\entry\\build\\default\\intermediates\\router_map\\default\\loader-router-map.json",{"fileSnapShotHashValue":"8ad7d2b2a35b677b01fd5aca18c477b1a8328a872b58e75b0c00d9564f08793b"}]]}},":CanvasComponent-master:entry:default@ProcessShareConfig":{"_inputs":[{"dataType":"ValueEntry","value":"{\"_name\":\"BUILTIN_TASK_COMMAND\",\"_value\":\"\",\"_valueType\":\"string\"}"},{"dataType":"ValueEntry","value":"{\"_name\":\"BUILTIN_TASK_TOOLCHAIN\",\"_value\":\"\",\"_valueType\":\"string\"}"},{"dataType":"ValueEntry","value":"{\"_name\":\"BUILTIN_TASK_ENV\",\"_value\":\"\",\"_valueType\":\"string\"}"}],"_successful":true,"_projectName":"CanvasComponent-master","_moduleName":"entry","_taskName":"default@ProcessShareConfig","_key":":CanvasComponent-master:entry:default@ProcessShareConfig","_executionId":":CanvasComponent-master:entry:default@ProcessShareConfig:1776760995710","_inputFiles":{"dataType":"Map","value":[["D:\\CanvasComponent-master\\CanvasComponent-master\\entry\\oh-package.json5",{"fileSnapShotHashValue":"51341dc9e67eda76e64209637ff2fa8b5232746c669ee572dcfe96f48f41be54"}],["D:\\CanvasComponent-master\\CanvasComponent-master\\oh-package.json5",{"fileSnapShotHashValue":"d54b49750dc46278cc05687d29d23b93067242e663c8256750c4932a3f3100c9"}],["D:\\CanvasComponent-master\\CanvasComponent-master\\entry\\src\\main\\module.json5",{"fileSnapShotHashValue":"02877489faf83d8b7219a40eeeddcd5bdc4ef1c0d902aec1f87b44c681223613"}]]},"_outputFiles":{"dataType":"Map","value":[["D:\\CanvasComponent-master\\CanvasComponent-master\\entry\\build\\default\\intermediates\\share_config\\default\\temp-share-config.json",{"fileSnapShotHashValue":"15ed9c93d3e35bea371ea636ed2d3bba70c6cab8c72f1b060a9ca7149d4e188d"}]]}},":CanvasComponent-master:entry:default@ProcessStartupConfig":{"_inputs":[{"dataType":"ValueEntry","value":"{\"_name\":\"appStartupFileName\",\"_value\":\"\",\"_valueType\":\"string\"}"},{"dataType":"ValueEntry","value":"{\"_name\":\"useNormalizedOHMUrl\",\"_value\":false,\"_valueType\":\"boolean\"}"},{"dataType":"ValueEntry","value":"{\"_name\":\"shouldCollectPreloadSystemSo\",\"_value\":false,\"_valueType\":\"boolean\"}"},{"dataType":"ValueEntry","value":"{\"_name\":\"BUILTIN_TASK_COMMAND\",\"_value\":\"\",\"_valueType\":\"string\"}"},{"dataType":"ValueEntry","value":"{\"_name\":\"BUILTIN_TASK_TOOLCHAIN\",\"_value\":\"\",\"_valueType\":\"string\"}"},{"dataType":"ValueEntry","value":"{\"_name\":\"BUILTIN_TASK_ENV\",\"_value\":\"\",\"_valueType\":\"string\"}"}],"_successful":true,"_projectName":"CanvasComponent-master","_moduleName":"entry","_taskName":"default@ProcessStartupConfig","_key":":CanvasComponent-master:entry:default@ProcessStartupConfig","_executionId":":CanvasComponent-master:entry:default@ProcessStartupConfig:1776760995714","_inputFiles":{"dataType":"Map","value":[]},"_outputFiles":{"dataType":"Map","value":[["D:\\CanvasComponent-master\\CanvasComponent-master\\entry\\build\\default\\intermediates\\startup\\default\\startup_config.json",{"fileSnapShotHashValue":""}]]}},":CanvasComponent-master:entry:default@ProcessResource":{"_inputs":[{"dataType":"ValueEntry","value":"{\"_name\":\"resConfigJsonContent\",\"_value\":\"{\\\"configPath\\\":\\\"D:\\\\\\\\CanvasComponent-master\\\\\\\\CanvasComponent-master\\\\\\\\entry\\\\\\\\build\\\\\\\\default\\\\\\\\intermediates\\\\\\\\process_profile\\\\\\\\default\\\\\\\\module.json\\\",\\\"packageName\\\":\\\"com.example.canvascomponent\\\",\\\"output\\\":\\\"D:\\\\\\\\CanvasComponent-master\\\\\\\\CanvasComponent-master\\\\\\\\entry\\\\\\\\build\\\\\\\\default\\\\\\\\intermediates\\\\\\\\res\\\\\\\\default\\\",\\\"moduleNames\\\":\\\"entry\\\",\\\"ResourceTable\\\":[\\\"D:\\\\\\\\CanvasComponent-master\\\\\\\\CanvasComponent-master\\\\\\\\entry\\\\\\\\build\\\\\\\\default\\\\\\\\generated\\\\\\\\r\\\\\\\\default\\\\\\\\ResourceTable.h\\\"],\\\"applicationResource\\\":\\\"D:\\\\\\\\CanvasComponent-master\\\\\\\\CanvasComponent-master\\\\\\\\AppScope\\\\\\\\resources\\\",\\\"moduleResources\\\":[\\\"D:\\\\\\\\CanvasComponent-master\\\\\\\\CanvasComponent-master\\\\\\\\entry\\\\\\\\src\\\\\\\\main\\\\\\\\resources\\\"],\\\"dependencies\\\":[],\\\"iconCheck\\\":true,\\\"ids\\\":\\\"D:\\\\\\\\CanvasComponent-master\\\\\\\\CanvasComponent-master\\\\\\\\entry\\\\\\\\build\\\\\\\\default\\\\\\\\intermediates\\\\\\\\res\\\\\\\\default\\\\\\\\ids_map\\\",\\\"definedIds\\\":\\\"D:\\\\\\\\CanvasComponent-master\\\\\\\\CanvasComponent-master\\\\\\\\entry\\\\\\\\build\\\\\\\\default\\\\\\\\intermediates\\\\\\\\res\\\\\\\\default\\\\\\\\ids_map\\\\\\\\id_defined.json\\\",\\\"definedSysIds\\\":\\\"D:\\\\\\\\DevEco Studio\\\\\\\\sdk\\\\\\\\default\\\\\\\\hms\\\\\\\\toolchains\\\\\\\\id_defined.json\\\"}\",\"_valueType\":\"string\"}"},{"dataType":"ValueEntry","value":"{\"_name\":\"D:\\\\CanvasComponent-master\\\\CanvasComponent-master\\\\entry\\\\build\\\\default\\\\intermediates\\\\res\\\\default\\\\opt-compression.json\",\"_value\":\"{\\\"context\\\":{\\\"extensionPath\\\":\\\"D:\\\\\\\\DevEco Studio\\\\\\\\sdk\\\\\\\\default\\\\\\\\hms\\\\\\\\toolchains\\\\\\\\lib\\\\\\\\libimage_transcoder_shared.dll\\\"},\\\"compression\\\":{\\\"media\\\":{\\\"enable\\\":false},\\\"filters\\\":[]}}\",\"_valueType\":\"string\"}"},{"dataType":"ValueEntry","value":"{\"_name\":\"resource_str\",\"_value\":false,\"_valueType\":\"boolean\"}"},{"dataType":"ValueEntry","value":"{\"_name\":\"ignoreResourcePattern\",\"_value\":\"\",\"_valueType\":\"string\"}"},{"dataType":"ValueEntry","value":"{\"_name\":\"includeAppScopeRes\",\"_value\":\"\",\"_valueType\":\"string\"}"},{"dataType":"ValueEntry","value":"{\"_name\":\"BUILTIN_TASK_COMMAND\",\"_value\":\"\",\"_valueType\":\"string\"}"},{"dataType":"ValueEntry","value":"{\"_name\":\"BUILTIN_TASK_TOOLCHAIN\",\"_value\":\"\",\"_valueType\":\"string\"}"},{"dataType":"ValueEntry","value":"{\"_name\":\"BUILTIN_TASK_ENV\",\"_value\":\"\",\"_valueType\":\"string\"}"}],"_successful":true,"_projectName":"CanvasComponent-master","_moduleName":"entry","_taskName":"default@ProcessResource","_key":":CanvasComponent-master:entry:default@ProcessResource","_executionId":":CanvasComponent-master:entry:default@ProcessResource:1776760995721","_inputFiles":{"dataType":"Map","value":[]},"_outputFiles":{"dataType":"Map","value":[["D:\\CanvasComponent-master\\CanvasComponent-master\\entry\\build\\default\\intermediates\\res\\default\\resConfig.json",{"isDirectory":false,"fileSnapShotHashValue":"cb1bb882966103b71f89f3dbd478aa904eef7ce1db1d3790fb3ac7b9c8804afd"}],["D:\\CanvasComponent-master\\CanvasComponent-master\\entry\\build\\default\\intermediates\\res\\default\\opt-compression.json",{"isDirectory":false,"fileSnapShotHashValue":"9f137676ba68d3175dfa53271d415ea41d050dfd5c4d349af572039e7ba0a416"}]]}},":CanvasComponent-master:entry:default@GenerateLoaderJson":{"_inputs":[{"dataType":"ValueEntry","value":"{\"_name\":\"projectRootPath\",\"_value\":\"D:\\\\CanvasComponent-master\\\\CanvasComponent-master\",\"_valueType\":\"string\"}"},{"dataType":"ValueEntry","value":"{\"_name\":\"modulePathMap\",\"_value\":\"{\\\"entry\\\":\\\"D:\\\\\\\\CanvasComponent-master\\\\\\\\CanvasComponent-master\\\\\\\\entry\\\"}\",\"_valueType\":\"string\"}"},{"dataType":"ValueEntry","value":"{\"_name\":\"module_dependencies\",\"_value\":\"{}\",\"_valueType\":\"string\"}"},{"dataType":"ValueEntry","value":"{\"_name\":\"overrides\",\"_valueType\":\"undefined\"}"},{"dataType":"ValueEntry","value":"{\"_name\":\"project_dependencies\",\"_value\":\"{}\",\"_valueType\":\"string\"}"},{"dataType":"ValueEntry","value":"{\"_name\":\"useNormalizedOHMUrl\",\"_value\":false,\"_valueType\":\"boolean\"}"},{"dataType":"ValueEntry","value":"{\"_name\":\"isOhosTest\",\"_value\":false,\"_valueType\":\"boolean\"}"},{"dataType":"ValueEntry","value":"{\"_name\":\"isFullCompilationEnabled\",\"_value\":true,\"_valueType\":\"boolean\"}"},{"dataType":"ValueEntry","value":"{\"_name\":\"patchConfig\",\"_value\":\"{\\\"changedFileList\\\":\\\"D:\\\\\\\\CanvasComponent-master\\\\\\\\CanvasComponent-master\\\\\\\\entry\\\\\\\\build\\\\\\\\default\\\\\\\\intermediates\\\\\\\\patch\\\\\\\\default\\\\\\\\changedFileList.json\\\"}\",\"_valueType\":\"string\"}"},{"dataType":"ValueEntry","value":"{\"_name\":\"appStartupFileName\",\"_value\":\"\",\"_valueType\":\"string\"}"},{"dataType":"ValueEntry","value":"{\"_name\":\"compileMode\",\"_value\":\"esmodule\",\"_valueType\":\"string\"}"},{"dataType":"ValueEntry","value":"{\"_name\":\"nodeModulesPath\",\"_value\":\"D:\\\\CanvasComponent-master\\\\CanvasComponent-master\\\\entry\\\\build\\\\default\\\\intermediates\\\\loader_out\\\\default\\\\node_modules\",\"_valueType\":\"string\"}"},{"dataType":"ValueEntry","value":"{\"_name\":\"targetConfig\",\"_value\":\"{\\\"name\\\":\\\"default\\\",\\\"runtimeOS\\\":\\\"HarmonyOS\\\"}\",\"_valueType\":\"string\"}"},{"dataType":"ValueEntry","value":"{\"_name\":\"hspNameOhmMap\",\"_value\":\"{}\",\"_valueType\":\"string\"}"},{"dataType":"ValueEntry","value":"{\"_name\":\"harNameOhmMap\",\"_value\":\"{}\",\"_valueType\":\"string\"}"},{"dataType":"ValueEntry","value":"{\"_name\":\"anBuildMode\",\"_value\":\"type\",\"_valueType\":\"string\"}"},{"dataType":"ValueEntry","value":"{\"_name\":\"apPath\",\"_value\":\"D:\\\\CanvasComponent-master\\\\CanvasComponent-master\\\\entry\\\\modules.ap\",\"_valueType\":\"string\"}"},{"dataType":"ValueEntry","value":"{\"_name\":\"fallbackAnBuild\",\"_value\":false,\"_valueType\":\"boolean\"}"},{"dataType":"ValueEntry","value":"{\"_name\":\"isHarWithCoverage\",\"_value\":false,\"_valueType\":\"boolean\"}"},{"dataType":"ValueEntry","value":"{\"_name\":\"compileApiVersion\",\"_value\":22,\"_valueType\":\"number\"}"},{"dataType":"ValueEntry","value":"{\"_name\":\"compatibleApiVersion\",\"_value\":17,\"_valueType\":\"number\"}"},{"dataType":"ValueEntry","value":"{\"_name\":\"isByteCodeHar\",\"_value\":false,\"_valueType\":\"boolean\"}"},{"dataType":"ValueEntry","value":"{\"_name\":\"shouldTreatHarAsHap\",\"_value\":false,\"_valueType\":\"boolean\"}"},{"dataType":"ValueEntry","value":"{\"_name\":\"isBundledDependencies\",\"_value\":false,\"_valueType\":\"boolean\"}"},{"dataType":"ValueEntry","value":"{\"_name\":\"needSubmitArkTsWidget\",\"_value\":false,\"_valueType\":\"boolean\"}"},{"dataType":"ValueEntry","value":"{\"_name\":\"isCustomizedHar\",\"_value\":false,\"_valueType\":\"boolean\"}"},{"dataType":"ValueEntry","value":"{\"_name\":\"isByteCodeHarOptimize\",\"_value\":false,\"_valueType\":\"boolean\"}"},{"dataType":"ValueEntry","value":"{\"_name\":\"BUILTIN_TASK_COMMAND\",\"_value\":\"\",\"_valueType\":\"string\"}"},{"dataType":"ValueEntry","value":"{\"_name\":\"BUILTIN_TASK_TOOLCHAIN\",\"_value\":\"\",\"_valueType\":\"string\"}"},{"dataType":"ValueEntry","value":"{\"_name\":\"BUILTIN_TASK_ENV\",\"_value\":\"\",\"_valueType\":\"string\"}"}],"_successful":true,"_projectName":"CanvasComponent-master","_moduleName":"entry","_taskName":"default@GenerateLoaderJson","_key":":CanvasComponent-master:entry:default@GenerateLoaderJson","_executionId":":CanvasComponent-master:entry:default@GenerateLoaderJson:1776760995730","_inputFiles":{"dataType":"Map","value":[["D:\\CanvasComponent-master\\CanvasComponent-master\\entry\\build\\default\\intermediates\\router_map\\default\\temp-router-map.json",{"fileSnapShotHashValue":"cb870ddb3078e4decce779a4945ca28e92b0187c5dae928b3021ce5a15d60cf8"}]]},"_outputFiles":{"dataType":"Map","value":[["D:\\CanvasComponent-master\\CanvasComponent-master\\entry\\build\\default\\intermediates\\loader\\default\\loader.json",{"isDirectory":false,"fileSnapShotHashValue":"e68106e658f68447841281108b3815c43ec9bd3d41b8c379a11fd537cde311a6"}]]}},":CanvasComponent-master:entry:default@ProcessLibs":{"_inputs":[{"dataType":"ValueEntry","value":"{\"_name\":\"isBundledDependencies\",\"_value\":false,\"_valueType\":\"boolean\"}"},{"dataType":"ValueEntry","value":"{\"_name\":\"isByteCodeHar\",\"_value\":false,\"_valueType\":\"boolean\"}"},{"dataType":"ValueEntry","value":"{\"_name\":\"excludeFromHar\",\"_value\":true,\"_valueType\":\"boolean\"}"},{"dataType":"ValueEntry","value":"{\"_name\":\"BUILTIN_TASK_COMMAND\",\"_value\":\"\",\"_valueType\":\"string\"}"},{"dataType":"ValueEntry","value":"{\"_name\":\"BUILTIN_TASK_TOOLCHAIN\",\"_value\":\"\",\"_valueType\":\"string\"}"},{"dataType":"ValueEntry","value":"{\"_name\":\"BUILTIN_TASK_ENV\",\"_value\":\"\",\"_valueType\":\"string\"}"}],"_successful":true,"_projectName":"CanvasComponent-master","_moduleName":"entry","_taskName":"default@ProcessLibs","_key":":CanvasComponent-master:entry:default@ProcessLibs","_executionId":":CanvasComponent-master:entry:default@ProcessLibs:1776760995739","_inputFiles":{"dataType":"Map","value":[["D:\\CanvasComponent-master\\CanvasComponent-master\\build-profile.json5",{"fileSnapShotHashValue":"9d31cba1b960957eb03f3edbd1f5d25f17a6a3193ba7426774a7b879ba897955"}],["D:\\CanvasComponent-master\\CanvasComponent-master\\entry\\build-profile.json5",{"fileSnapShotHashValue":"53da7afe97d8956c4632345d102292b37a8a8220432246269ca0cb8e26745b9f"}]]},"_outputFiles":{"dataType":"Map","value":[["D:\\CanvasComponent-master\\CanvasComponent-master\\entry\\build\\default\\intermediates\\libs\\default",{"isDirectory":true,"fileSnapShotHashValue":""}]]}},":CanvasComponent-master:entry:default@CompileResource":{"_inputs":[{"dataType":"ValueEntry","value":"{\"_name\":\"TARGET_CONFIG\",\"_value\":\"{\\\"name\\\":\\\"default\\\",\\\"runtimeOS\\\":\\\"HarmonyOS\\\"}\",\"_valueType\":\"string\"}"},{"dataType":"ValueEntry","value":"{\"_name\":\"useNormalizedOHMUrl\",\"_value\":false,\"_valueType\":\"boolean\"}"},{"dataType":"ValueEntry","value":"{\"_name\":\"BUILTIN_TASK_COMMAND\",\"_value\":\"D:\\\\DevEco Studio\\\\sdk\\\\default\\\\openharmony\\\\toolchains\\\\restool.exe,-l,D:\\\\CanvasComponent-master\\\\CanvasComponent-master\\\\entry\\\\build\\\\default\\\\intermediates\\\\res\\\\default\\\\resConfig.json\",\"_valueType\":\"string\"}"},{"dataType":"ValueEntry","value":"{\"_name\":\"BUILTIN_TASK_TOOLCHAIN\",\"_value\":\"D:\\\\DevEco Studio\\\\sdk\\\\default\\\\openharmony\\\\toolchains\\\\restool.exe\",\"_valueType\":\"string\"}"},{"dataType":"ValueEntry","value":"{\"_name\":\"BUILTIN_TASK_ENV\",\"_value\":\"\",\"_valueType\":\"string\"}"}],"_successful":true,"_projectName":"CanvasComponent-master","_moduleName":"entry","_taskName":"default@CompileResource","_key":":CanvasComponent-master:entry:default@CompileResource","_executionId":":CanvasComponent-master:entry:default@CompileResource:1776760995748","_inputFiles":{"dataType":"Map","value":[["D:\\CanvasComponent-master\\CanvasComponent-master\\entry\\src\\main\\resources",{"fileSnapShotHashValue":"3cd953e7feecb8e6f949350f6abeab4afb87bb1c13bb358ae8fe2715dbd33ba6"}],["D:\\CanvasComponent-master\\CanvasComponent-master\\AppScope\\resources",{"fileSnapShotHashValue":"794e5a9103ba6c6840391ecd05da8dcf389d873f45dafcf79c4a50d56a567abe"}],["D:\\CanvasComponent-master\\CanvasComponent-master\\entry\\build\\default\\intermediates\\process_profile\\default\\module.json",{"isDirectory":false,"fileSnapShotHashValue":"a7bab3715ca865badc3a3b67b45176eb69f8792b9a6d489187c27282ea9816d9"}],["D:\\CanvasComponent-master\\CanvasComponent-master\\entry\\build\\default\\intermediates\\res\\default\\resConfig.json",{"isDirectory":false,"fileSnapShotHashValue":"cb1bb882966103b71f89f3dbd478aa904eef7ce1db1d3790fb3ac7b9c8804afd"}]]},"_outputFiles":{"dataType":"Map","value":[["D:\\CanvasComponent-master\\CanvasComponent-master\\entry\\build\\default\\intermediates\\res\\default",{"isDirectory":true,"fileSnapShotHashValue":"b9789a3cd10b708f40ad6a8c872a09cb8d4e7a0499916e8d5b0aa314b5d4ffc7"}],["D:\\CanvasComponent-master\\CanvasComponent-master\\entry\\build\\default\\generated\\r\\default\\ResourceTable.h",{"isDirectory":false,"fileSnapShotHashValue":"e0564215ecd4c67b3024c5788cb1f38abf2718a23452a06d49034931ffb7ada7"}],["D:\\CanvasComponent-master\\CanvasComponent-master\\entry\\build\\default\\generated\\r\\default",{"isDirectory":true,"fileSnapShotHashValue":"6b201cb14dd79ad3a4fb399b387ef0f4634bfe054a2ebe07db7f1abe251b2027"}]]}},":CanvasComponent-master:entry:default@DoNativeStrip":{"_inputs":[{"dataType":"ValueEntry","value":"{\"_name\":\"debugSymbol\",\"_value\":\"\",\"_valueType\":\"string\"}"},{"dataType":"ValueEntry","value":"{\"_name\":\"BUILTIN_TASK_COMMAND\",\"_value\":\"\",\"_valueType\":\"string\"}"},{"dataType":"ValueEntry","value":"{\"_name\":\"BUILTIN_TASK_TOOLCHAIN\",\"_value\":\"\",\"_valueType\":\"string\"}"},{"dataType":"ValueEntry","value":"{\"_name\":\"BUILTIN_TASK_ENV\",\"_value\":\"\",\"_valueType\":\"string\"}"}],"_successful":true,"_projectName":"CanvasComponent-master","_moduleName":"entry","_taskName":"default@DoNativeStrip","_key":":CanvasComponent-master:entry:default@DoNativeStrip","_executionId":":CanvasComponent-master:entry:default@DoNativeStrip:1776760996636","_inputFiles":{"dataType":"Map","value":[["D:\\CanvasComponent-master\\CanvasComponent-master\\entry\\build\\default\\intermediates\\libs\\default",{"isDirectory":true,"fileSnapShotHashValue":""}]]},"_outputFiles":{"dataType":"Map","value":[["D:\\CanvasComponent-master\\CanvasComponent-master\\entry\\build\\default\\intermediates\\stripped_native_libs\\default",{"isDirectory":true,"fileSnapShotHashValue":""}]]}},":CanvasComponent-master:entry:default@CompileArkTS":{"_inputs":[{"dataType":"ValueEntry","value":"{\"_name\":\"debuggable\",\"_value\":true,\"_valueType\":\"boolean\"}"},{"dataType":"ValueEntry","value":"{\"_name\":\"isArk\",\"_value\":true,\"_valueType\":\"boolean\"}"},{"dataType":"ValueEntry","value":"{\"_name\":\"needCoverageInsert\",\"_value\":false,\"_valueType\":\"boolean\"}"},{"dataType":"ValueEntry","value":"{\"_name\":\"ark.tsImportSendable\",\"_value\":false,\"_valueType\":\"boolean\"}"},{"dataType":"ValueEntry","value":"{\"_name\":\"customTypes\",\"_value\":[],\"_valueType\":\"object\"}"},{"dataType":"ValueEntry","value":"{\"_name\":\"isByteCodeHarOptimize\",\"_value\":false,\"_valueType\":\"boolean\"}"},{"dataType":"ValueEntry","value":"{\"_name\":\"caseSensitiveCheck\",\"_value\":false,\"_valueType\":\"boolean\"}"},{"dataType":"ValueEntry","value":"{\"_name\":\"useNormalizedOHMUrl\",\"_value\":false,\"_valueType\":\"boolean\"}"},{"dataType":"ValueEntry","value":"{\"_name\":\"transformLib\",\"_value\":\"\",\"_valueType\":\"string\"}"},{"dataType":"ValueEntry","value":"{\"_name\":\"compatibleSdkVersionStage\",\"_value\":\"\",\"_valueType\":\"string\"}"},{"dataType":"ValueEntry","value":"{\"_name\":\"skipOhModulesLint\",\"_value\":false,\"_valueType\":\"boolean\"}"},{"dataType":"ValueEntry","value":"{\"_name\":\"autoLazyImport\",\"_value\":false,\"_valueType\":\"boolean\"}"},{"dataType":"ValueEntry","value":"{\"_name\":\"allowEmptyBundleName\",\"_value\":false,\"_valueType\":\"boolean\"}"},{"dataType":"ValueEntry","value":"{\"_name\":\"reExportCheckMode\",\"_value\":\"noCheck\",\"_valueType\":\"string\"}"},{"dataType":"ValueEntry","value":"{\"_name\":\"executionMode\",\"_value\":\"memory\",\"_valueType\":\"string\"}"},{"dataType":"ValueEntry","value":"{\"_name\":\"usePathPlaceholder\",\"_value\":false,\"_valueType\":\"boolean\"}"},{"dataType":"ValueEntry","value":"{\"_name\":\"writeRollupCache\",\"_value\":true,\"_valueType\":\"boolean\"}"},{"dataType":"ValueEntry","value":"{\"_name\":\"isExpandImportEnabled\",\"_value\":false,\"_valueType\":\"boolean\"}"},{"dataType":"ValueEntry","value":"{\"_name\":\"expandImportExclude\",\"_value\":\"\",\"_valueType\":\"string\"}"},{"dataType":"ValueEntry","value":"{\"_name\":\"lazyImportExclude\",\"_value\":\"\",\"_valueType\":\"string\"}"},{"dataType":"ValueEntry","value":"{\"_name\":\"lazyImportInclude\",\"_value\":\"\",\"_valueType\":\"string\"}"},{"dataType":"ValueEntry","value":"{\"_name\":\"ignoreCrossplatformCheck\",\"_value\":false,\"_valueType\":\"boolean\"}"},{"dataType":"ValueEntry","value":"{\"_name\":\"isHarDeduplicateEnabled\",\"_value\":false,\"_valueType\":\"boolean\"}"},{"dataType":"ValueEntry","value":"{\"_name\":\"enableStrictCheckOHModule\",\"_value\":false,\"_valueType\":\"boolean\"}"},{"dataType":"ValueEntry","value":"{\"_name\":\"disableSendableCheckRules\",\"_value\":[],\"_valueType\":\"object\"}"},{"dataType":"ValueEntry","value":"{\"_name\":\"useDeclarationFileSignature\",\"_value\":false,\"_valueType\":\"boolean\"}"},{"dataType":"ValueEntry","value":"{\"_name\":\"customizedOptions\",\"_value\":\"\",\"_valueType\":\"string\"}"},{"dataType":"ValueEntry","value":"{\"_name\":\"integratedHsp\",\"_value\":false,\"_valueType\":\"boolean\"}"},{"dataType":"ValueEntry","value":"{\"_name\":\"isPreloadSoEnabled\",\"_value\":false,\"_valueType\":\"boolean\"}"},{"dataType":"ValueEntry","value":"{\"_name\":\"arkTsWdiget\",\"_value\":false,\"_valueType\":\"boolean\"}"},{"dataType":"ValueEntry","value":"{\"_name\":\"OBFUSCATION_ENABLE\",\"_value\":\"undefined\",\"_valueType\":\"string\"}"},{"dataType":"ValueEntry","value":"{\"_name\":\"OBFUSCATION_FILES_HASH\",\"_value\":\"\",\"_valueType\":\"string\"}"},{"dataType":"ValueEntry","value":"{\"_name\":\"maxFlowDepth\",\"_value\":\"undefined\",\"_valueType\":\"string\"}"},{"dataType":"ValueEntry","value":"{\"_name\":\"noExternalImportByPath\",\"_value\":false,\"_valueType\":\"boolean\"}"},{"dataType":"ValueEntry","value":"{\"_name\":\"copyCodeResourceEnable\",\"_value\":true,\"_valueType\":\"boolean\"}"},{"dataType":"ValueEntry","value":"{\"_name\":\"copyCodeResourceExcludes\",\"_value\":[],\"_valueType\":\"object\"}"},{"dataType":"ValueEntry","value":"{\"_name\":\"copyCodeResourceIncludes\",\"_value\":\"undefined\",\"_valueType\":\"string\"}"},{"dataType":"ValueEntry","value":"{\"_name\":\"ohos.uiTransform.Optimization\",\"_value\":false,\"_valueType\":\"boolean\"}"},{"dataType":"ValueEntry","value":"{\"_name\":\"ohos.rollupCache.useSourceHash\",\"_value\":false,\"_valueType\":\"boolean\"}"},{"dataType":"ValueEntry","value":"{\"_name\":\"localModuleParamMap\",\"_value\":\"{}\",\"_valueType\":\"string\"}"},{"dataType":"ValueEntry","value":"{\"_name\":\"autoLazyFilter\",\"_value\":\"\",\"_valueType\":\"string\"}"},{"dataType":"ValueEntry","value":"{\"_name\":\"BUILTIN_TASK_COMMAND\",\"_value\":\"\",\"_valueType\":\"string\"}"},{"dataType":"ValueEntry","value":"{\"_name\":\"BUILTIN_TASK_TOOLCHAIN\",\"_value\":\"\",\"_valueType\":\"string\"}"},{"dataType":"ValueEntry","value":"{\"_name\":\"BUILTIN_TASK_ENV\",\"_value\":\"\",\"_valueType\":\"string\"}"}],"_successful":true,"_projectName":"CanvasComponent-master","_moduleName":"entry","_taskName":"default@CompileArkTS","_key":":CanvasComponent-master:entry:default@CompileArkTS","_executionId":":CanvasComponent-master:entry:default@CompileArkTS:1776760996649","_inputFiles":{"dataType":"Map","value":[["D:\\CanvasComponent-master\\CanvasComponent-master\\entry\\build\\default\\intermediates\\loader\\default",{"isDirectory":true,"fileSnapShotHashValue":"bd8e9fbc45e04bb8ebbd0f25fda3d841d070d2a4955e2736e3f12485fc191cc0"}],["D:\\CanvasComponent-master\\CanvasComponent-master\\entry\\build\\default\\intermediates\\res\\default\\ResourceTable.txt",{"fileSnapShotHashValue":"de8229c0d6b4f2846a0980a6bde48a96fbc42a6778afdda4dba143077d2e745b"}],["D:\\CanvasComponent-master\\CanvasComponent-master\\entry\\build\\default\\intermediates\\res\\default\\ark_module.json",{"fileSnapShotHashValue":"b71bc714ad9f1db869389007ddbcbc434496b272ef195d51a7a0d8911c7206cc"}],["D:\\CanvasComponent-master\\CanvasComponent-master\\entry\\build\\default\\intermediates\\res\\default\\resources\\base\\profile",{"isDirectory":true,"fileSnapShotHashValue":"21e81352595bb6f0f0f79a49a088ff5436f776ea081ec2f3485a129610d32540"}],["D:\\CanvasComponent-master\\CanvasComponent-master\\entry\\src\\main\\ets",{"isDirectory":true,"fileSnapShotHashValue":"4ba77e371ac8d8975e127515fb7c1934b90343138836e996e834f4b447ed9ac7"}],["D:\\CanvasComponent-master\\CanvasComponent-master\\entry\\build\\default\\generated\\profile\\default\\BuildProfile.ets",{"fileSnapShotHashValue":"acf4793b117a82f865112500fa5a2ea62987ab6caee7e85d030b5af044ff7cb3"}]]},"_outputFiles":{"dataType":"Map","value":[["D:\\CanvasComponent-master\\CanvasComponent-master\\entry\\build\\default\\intermediates\\loader_out\\default\\ets",{"isDirectory":true,"fileSnapShotHashValue":"b47b2e4babf5e2dddd094e27d7a276083a64cc6e84aef4253065709c83c6e7e3"}]]}},":CanvasComponent-master:entry:default@BuildJS":{"_inputs":[{"dataType":"ValueEntry","value":"{\"_name\":\"debuggable\",\"_value\":true,\"_valueType\":\"boolean\"}"},{"dataType":"ValueEntry","value":"{\"_name\":\"isArk\",\"_value\":true,\"_valueType\":\"boolean\"}"},{"dataType":"ValueEntry","value":"{\"_name\":\"needCoverageInsert\",\"_value\":false,\"_valueType\":\"boolean\"}"},{"dataType":"ValueEntry","value":"{\"_name\":\"ark.tsImportSendable\",\"_value\":false,\"_valueType\":\"boolean\"}"},{"dataType":"ValueEntry","value":"{\"_name\":\"customTypes\",\"_value\":[],\"_valueType\":\"object\"}"},{"dataType":"ValueEntry","value":"{\"_name\":\"isByteCodeHarOptimize\",\"_value\":false,\"_valueType\":\"boolean\"}"},{"dataType":"ValueEntry","value":"{\"_name\":\"caseSensitiveCheck\",\"_value\":false,\"_valueType\":\"boolean\"}"},{"dataType":"ValueEntry","value":"{\"_name\":\"useNormalizedOHMUrl\",\"_value\":false,\"_valueType\":\"boolean\"}"},{"dataType":"ValueEntry","value":"{\"_name\":\"transformLib\",\"_value\":\"\",\"_valueType\":\"string\"}"},{"dataType":"ValueEntry","value":"{\"_name\":\"compatibleSdkVersionStage\",\"_value\":\"\",\"_valueType\":\"string\"}"},{"dataType":"ValueEntry","value":"{\"_name\":\"skipOhModulesLint\",\"_value\":false,\"_valueType\":\"boolean\"}"},{"dataType":"ValueEntry","value":"{\"_name\":\"autoLazyImport\",\"_value\":false,\"_valueType\":\"boolean\"}"},{"dataType":"ValueEntry","value":"{\"_name\":\"allowEmptyBundleName\",\"_value\":false,\"_valueType\":\"boolean\"}"},{"dataType":"ValueEntry","value":"{\"_name\":\"reExportCheckMode\",\"_value\":\"noCheck\",\"_valueType\":\"string\"}"},{"dataType":"ValueEntry","value":"{\"_name\":\"executionMode\",\"_value\":\"memory\",\"_valueType\":\"string\"}"},{"dataType":"ValueEntry","value":"{\"_name\":\"usePathPlaceholder\",\"_value\":false,\"_valueType\":\"boolean\"}"},{"dataType":"ValueEntry","value":"{\"_name\":\"writeRollupCache\",\"_value\":true,\"_valueType\":\"boolean\"}"},{"dataType":"ValueEntry","value":"{\"_name\":\"isExpandImportEnabled\",\"_value\":false,\"_valueType\":\"boolean\"}"},{"dataType":"ValueEntry","value":"{\"_name\":\"expandImportExclude\",\"_value\":\"\",\"_valueType\":\"string\"}"},{"dataType":"ValueEntry","value":"{\"_name\":\"lazyImportExclude\",\"_value\":\"\",\"_valueType\":\"string\"}"},{"dataType":"ValueEntry","value":"{\"_name\":\"lazyImportInclude\",\"_value\":\"\",\"_valueType\":\"string\"}"},{"dataType":"ValueEntry","value":"{\"_name\":\"ignoreCrossplatformCheck\",\"_value\":false,\"_valueType\":\"boolean\"}"},{"dataType":"ValueEntry","value":"{\"_name\":\"isHarDeduplicateEnabled\",\"_value\":false,\"_valueType\":\"boolean\"}"},{"dataType":"ValueEntry","value":"{\"_name\":\"enableStrictCheckOHModule\",\"_value\":false,\"_valueType\":\"boolean\"}"},{"dataType":"ValueEntry","value":"{\"_name\":\"disableSendableCheckRules\",\"_value\":[],\"_valueType\":\"object\"}"},{"dataType":"ValueEntry","value":"{\"_name\":\"useDeclarationFileSignature\",\"_value\":false,\"_valueType\":\"boolean\"}"},{"dataType":"ValueEntry","value":"{\"_name\":\"customizedOptions\",\"_value\":\"\",\"_valueType\":\"string\"}"},{"dataType":"ValueEntry","value":"{\"_name\":\"integratedHsp\",\"_value\":false,\"_valueType\":\"boolean\"}"},{"dataType":"ValueEntry","value":"{\"_name\":\"autoLazyFilter\",\"_value\":\"\",\"_valueType\":\"string\"}"},{"dataType":"ValueEntry","value":"{\"_name\":\"BUILTIN_TASK_COMMAND\",\"_value\":\"\",\"_valueType\":\"string\"}"},{"dataType":"ValueEntry","value":"{\"_name\":\"BUILTIN_TASK_TOOLCHAIN\",\"_value\":\"\",\"_valueType\":\"string\"}"},{"dataType":"ValueEntry","value":"{\"_name\":\"BUILTIN_TASK_ENV\",\"_value\":\"\",\"_valueType\":\"string\"}"}],"_successful":false,"_projectName":"CanvasComponent-master","_moduleName":"entry","_taskName":"default@BuildJS","_key":":CanvasComponent-master:entry:default@BuildJS","_executionId":":CanvasComponent-master:entry:default@BuildJS:1776760996683","_inputFiles":{"dataType":"Map","value":[["D:\\CanvasComponent-master\\CanvasComponent-master\\entry\\build\\default\\intermediates\\loader\\default",{"isDirectory":true,"fileSnapShotHashValue":"bd8e9fbc45e04bb8ebbd0f25fda3d841d070d2a4955e2736e3f12485fc191cc0"}],["D:\\CanvasComponent-master\\CanvasComponent-master\\entry\\build\\default\\intermediates\\res\\default\\ResourceTable.txt",{"fileSnapShotHashValue":"de8229c0d6b4f2846a0980a6bde48a96fbc42a6778afdda4dba143077d2e745b"}],["D:\\CanvasComponent-master\\CanvasComponent-master\\entry\\build\\default\\intermediates\\res\\default\\ark_module.json",{"fileSnapShotHashValue":"b71bc714ad9f1db869389007ddbcbc434496b272ef195d51a7a0d8911c7206cc"}],["D:\\CanvasComponent-master\\CanvasComponent-master\\entry\\build\\default\\intermediates\\res\\default\\resources\\base\\profile",{"isDirectory":true,"fileSnapShotHashValue":"21e81352595bb6f0f0f79a49a088ff5436f776ea081ec2f3485a129610d32540"}]]},"_outputFiles":{"dataType":"Map","value":[["D:\\CanvasComponent-master\\CanvasComponent-master\\entry\\build\\default\\intermediates\\loader_out\\default\\js",{"isDirectory":true,"fileSnapShotHashValue":""}]]}},":CanvasComponent-master:entry:default@CacheNativeLibs":{"_inputs":[{"dataType":"ValueEntry","value":"{\"_name\":\"debugSymbol\",\"_value\":\"\",\"_valueType\":\"string\"}"},{"dataType":"ValueEntry","value":"{\"_name\":\"BUILTIN_TASK_COMMAND\",\"_value\":\"\",\"_valueType\":\"string\"}"},{"dataType":"ValueEntry","value":"{\"_name\":\"BUILTIN_TASK_TOOLCHAIN\",\"_value\":\"\",\"_valueType\":\"string\"}"},{"dataType":"ValueEntry","value":"{\"_name\":\"BUILTIN_TASK_ENV\",\"_value\":\"\",\"_valueType\":\"string\"}"}],"_successful":true,"_projectName":"CanvasComponent-master","_moduleName":"entry","_taskName":"default@CacheNativeLibs","_key":":CanvasComponent-master:entry:default@CacheNativeLibs","_executionId":":CanvasComponent-master:entry:default@CacheNativeLibs:1776760996688","_inputFiles":{"dataType":"Map","value":[["D:\\CanvasComponent-master\\CanvasComponent-master\\entry\\build\\default\\intermediates\\stripped_native_libs\\default",{"isDirectory":true,"fileSnapShotHashValue":""}],["D:\\CanvasComponent-master\\CanvasComponent-master\\entry\\build\\default\\intermediates\\libs\\default",{"isDirectory":true,"fileSnapShotHashValue":""}]]},"_outputFiles":{"dataType":"Map","value":[["D:\\CanvasComponent-master\\CanvasComponent-master\\entry\\build\\default\\intermediates\\patch\\default\\base_native_libs.json",{"isDirectory":false,"fileSnapShotHashValue":"bec55212d79ebaed21b45dd97609125db7af823ac2b30def09a6f51f2bc8d402"}]]}},":CanvasComponent-master:entry:default@GeneratePkgModuleJson":{"_inputs":[{"dataType":"ValueEntry","value":"{\"_name\":\"BUILTIN_TASK_COMMAND\",\"_value\":\"\",\"_valueType\":\"string\"}"},{"dataType":"ValueEntry","value":"{\"_name\":\"BUILTIN_TASK_TOOLCHAIN\",\"_value\":\"\",\"_valueType\":\"string\"}"},{"dataType":"ValueEntry","value":"{\"_name\":\"BUILTIN_TASK_ENV\",\"_value\":\"\",\"_valueType\":\"string\"}"}],"_successful":true,"_projectName":"CanvasComponent-master","_moduleName":"entry","_taskName":"default@GeneratePkgModuleJson","_key":":CanvasComponent-master:entry:default@GeneratePkgModuleJson","_executionId":":CanvasComponent-master:entry:default@GeneratePkgModuleJson:1776761005401","_inputFiles":{"dataType":"Map","value":[["D:\\CanvasComponent-master\\CanvasComponent-master\\entry\\build\\default\\intermediates\\res\\default\\module.json",{"fileSnapShotHashValue":"95cc5651eaba85660afd058dec4be2f0017c9777135dc96080d2d5b3e119b536"}]]},"_outputFiles":{"dataType":"Map","value":[["D:\\CanvasComponent-master\\CanvasComponent-master\\entry\\build\\default\\intermediates\\package\\default\\module.json",{"fileSnapShotHashValue":"307401b49c55845ed962823cacc81e43e5cbcb1a2410ab94fca609d973a46035"}]]}},":CanvasComponent-master:entry:default@ProcessCompiledResources":{"_inputs":[{"dataType":"ValueEntry","value":"{\"_name\":\"resourcePath\",\"_value\":\"D:\\\\CanvasComponent-master\\\\CanvasComponent-master\\\\entry\\\\build\\\\default\\\\intermediates\\\\res\\\\default\\\\resources\",\"_valueType\":\"string\"}"},{"dataType":"ValueEntry","value":"{\"_name\":\"BUILTIN_TASK_COMMAND\",\"_value\":\"\",\"_valueType\":\"string\"}"},{"dataType":"ValueEntry","value":"{\"_name\":\"BUILTIN_TASK_TOOLCHAIN\",\"_value\":\"\",\"_valueType\":\"string\"}"},{"dataType":"ValueEntry","value":"{\"_name\":\"BUILTIN_TASK_ENV\",\"_value\":\"\",\"_valueType\":\"string\"}"}],"_successful":false,"_projectName":"CanvasComponent-master","_moduleName":"entry","_taskName":"default@ProcessCompiledResources","_key":":CanvasComponent-master:entry:default@ProcessCompiledResources","_executionId":":CanvasComponent-master:entry:default@ProcessCompiledResources:1776761005405","_inputFiles":{"dataType":"Map","value":[]},"_outputFiles":{"dataType":"Map","value":[]}},":CanvasComponent-master:entry:default@PackageHap":{"_inputs":[{"dataType":"ValueEntry","value":"{\"_name\":\"hotReload\",\"_value\":false,\"_valueType\":\"boolean\"}"},{"dataType":"ValueEntry","value":"{\"_name\":\"integrated_hsp\",\"_value\":false,\"_valueType\":\"boolean\"}"},{"dataType":"ValueEntry","value":"{\"_name\":\"projectConfigAppOpt\",\"_valueType\":\"undefined\"}"},{"dataType":"ValueEntry","value":"{\"_name\":\"sourceMapDir\",\"_value\":\"\",\"_valueType\":\"string\"}"},{"dataType":"ValueEntry","value":"{\"_name\":\"bundleType\",\"_value\":\"app\",\"_valueType\":\"string\"}"},{"dataType":"ValueEntry","value":"{\"_name\":\"BUILTIN_TASK_COMMAND\",\"_value\":\"java,-Dfile.encoding=GBK,-jar,D:\\\\DevEco Studio\\\\sdk\\\\default\\\\openharmony\\\\toolchains\\\\lib\\\\app_packing_tool.jar,--mode,hap,--force,true,--lib-path,D:\\\\CanvasComponent-master\\\\CanvasComponent-master\\\\entry\\\\build\\\\default\\\\intermediates\\\\stripped_native_libs\\\\default,--json-path,D:\\\\CanvasComponent-master\\\\CanvasComponent-master\\\\entry\\\\build\\\\default\\\\intermediates\\\\package\\\\default\\\\module.json,--resources-path,D:\\\\CanvasComponent-master\\\\CanvasComponent-master\\\\entry\\\\build\\\\default\\\\intermediates\\\\res\\\\default\\\\resources,--index-path,D:\\\\CanvasComponent-master\\\\CanvasComponent-master\\\\entry\\\\build\\\\default\\\\intermediates\\\\res\\\\default\\\\resources.index,--pack-info-path,D:\\\\CanvasComponent-master\\\\CanvasComponent-master\\\\entry\\\\build\\\\default\\\\outputs\\\\default\\\\pack.info,--out-path,D:\\\\CanvasComponent-master\\\\CanvasComponent-master\\\\entry\\\\build\\\\default\\\\outputs\\\\default\\\\entry-default-unsigned.hap,--ets-path,D:\\\\CanvasComponent-master\\\\CanvasComponent-master\\\\entry\\\\build\\\\default\\\\intermediates\\\\loader_out\\\\default\\\\ets\",\"_valueType\":\"string\"}"},{"dataType":"ValueEntry","value":"{\"_name\":\"BUILTIN_TASK_TOOLCHAIN\",\"_value\":\"D:\\\\DevEco Studio\\\\sdk\\\\default\\\\openharmony\\\\toolchains\\\\lib\\\\app_packing_tool.jar\",\"_valueType\":\"string\"}"},{"dataType":"ValueEntry","value":"{\"_name\":\"BUILTIN_TASK_ENV\",\"_value\":\"\",\"_valueType\":\"string\"}"}],"_successful":true,"_projectName":"CanvasComponent-master","_moduleName":"entry","_taskName":"default@PackageHap","_key":":CanvasComponent-master:entry:default@PackageHap","_executionId":":CanvasComponent-master:entry:default@PackageHap:1776761005411","_inputFiles":{"dataType":"Map","value":[["D:\\CanvasComponent-master\\CanvasComponent-master\\entry\\build\\default\\intermediates\\stripped_native_libs\\default",{"isDirectory":false,"fileSnapShotHashValue":""}],["D:\\CanvasComponent-master\\CanvasComponent-master\\entry\\build\\default\\intermediates\\res\\default\\module.json",{"isDirectory":false,"fileSnapShotHashValue":"95cc5651eaba85660afd058dec4be2f0017c9777135dc96080d2d5b3e119b536"}],["D:\\CanvasComponent-master\\CanvasComponent-master\\entry\\build\\default\\intermediates\\res\\default\\resources",{"isDirectory":false,"fileSnapShotHashValue":"a150e79a3e8f83edbb6dd0add4618bba62c8e5f5507fd30aca20398bdb06b0b7"}],["D:\\CanvasComponent-master\\CanvasComponent-master\\entry\\build\\default\\intermediates\\res\\default\\resources.index",{"isDirectory":false,"fileSnapShotHashValue":"df83813cd93896234283ce911f0719cdd9ec52389fc467181451651ee017120b"}],["D:\\CanvasComponent-master\\CanvasComponent-master\\entry\\build\\default\\outputs\\default\\pack.info",{"isDirectory":false,"fileSnapShotHashValue":"779ad8a14a2cae4ec2a1276a51b649e9b5a39772ef3a30d095099d8f41fe00f2"}],["D:\\CanvasComponent-master\\CanvasComponent-master\\entry\\build\\default\\intermediates\\loader_out\\default\\ets",{"isDirectory":false,"fileSnapShotHashValue":"b47b2e4babf5e2dddd094e27d7a276083a64cc6e84aef4253065709c83c6e7e3"}],["D:\\CanvasComponent-master\\CanvasComponent-master\\entry\\build\\default\\intermediates\\loader_out\\default\\ets\\sourceMaps.map",{"isDirectory":false,"fileSnapShotHashValue":"a6299c0f5bb71ed93ecfc3d09476957805f6606c7ee39f3d6c4b781fc7231c01"}],["D:\\CanvasComponent-master\\CanvasComponent-master\\entry\\build\\default\\generated\\profile\\default\\BuildProfile.ets",{"fileSnapShotHashValue":"acf4793b117a82f865112500fa5a2ea62987ab6caee7e85d030b5af044ff7cb3"}]]},"_outputFiles":{"dataType":"Map","value":[["D:\\CanvasComponent-master\\CanvasComponent-master\\entry\\build\\default\\outputs\\default\\entry-default-unsigned.hap",{"isDirectory":false,"fileSnapShotHashValue":"7e6db0603bfa11371df32f4728af3618f914f4d56debad62c5ae3a0a555a6c8d"}],["D:\\CanvasComponent-master\\CanvasComponent-master\\entry\\build\\default\\intermediates\\source_map\\default\\sourceMaps.map",{"fileSnapShotHashValue":"a6299c0f5bb71ed93ecfc3d09476957805f6606c7ee39f3d6c4b781fc7231c01"}],["D:\\CanvasComponent-master\\CanvasComponent-master\\entry\\build\\default\\outputs\\default\\mapping\\sourceMaps.map",{"fileSnapShotHashValue":"a6299c0f5bb71ed93ecfc3d09476957805f6606c7ee39f3d6c4b781fc7231c01"}]]}},":CanvasComponent-master:entry:default@SignHap":{"_inputs":[{"dataType":"ValueEntry","value":"{\"_name\":\"enableSignTask\",\"_value\":true,\"_valueType\":\"boolean\"}"},{"dataType":"ValueEntry","value":"{\"_name\":\"sdkToolchainsComponentVersion\",\"_value\":\"6.0.2.130\",\"_valueType\":\"string\"}"},{"dataType":"ValueEntry","value":"{\"_name\":\"existSigningConfig\",\"_value\":false,\"_valueType\":\"boolean\"}"},{"dataType":"ValueEntry","value":"{\"_name\":\"BUILTIN_TASK_COMMAND\",\"_value\":\"\",\"_valueType\":\"string\"}"},{"dataType":"ValueEntry","value":"{\"_name\":\"BUILTIN_TASK_TOOLCHAIN\",\"_value\":\"\",\"_valueType\":\"string\"}"},{"dataType":"ValueEntry","value":"{\"_name\":\"BUILTIN_TASK_ENV\",\"_value\":\"\",\"_valueType\":\"string\"}"}],"_successful":true,"_projectName":"CanvasComponent-master","_moduleName":"entry","_taskName":"default@SignHap","_key":":CanvasComponent-master:entry:default@SignHap","_executionId":":CanvasComponent-master:entry:default@SignHap:1776761005799","_inputFiles":{"dataType":"Map","value":[["D:\\CanvasComponent-master\\CanvasComponent-master\\entry\\build\\default\\outputs\\default\\entry-default-unsigned.hap",{"isDirectory":false,"fileSnapShotHashValue":"7e6db0603bfa11371df32f4728af3618f914f4d56debad62c5ae3a0a555a6c8d"}]]},"_outputFiles":{"dataType":"Map","value":[["D:\\CanvasComponent-master\\CanvasComponent-master\\entry\\build\\default\\outputs\\default\\entry-default-signed.hap",{"isDirectory":false,"fileSnapShotHashValue":""}]]}},":CanvasComponent-master:entry:default@CollectDebugSymbol":{"_inputs":[{"dataType":"ValueEntry","value":"{\"_name\":\"BUILTIN_TASK_COMMAND\",\"_value\":\"\",\"_valueType\":\"string\"}"},{"dataType":"ValueEntry","value":"{\"_name\":\"BUILTIN_TASK_TOOLCHAIN\",\"_value\":\"\",\"_valueType\":\"string\"}"},{"dataType":"ValueEntry","value":"{\"_name\":\"BUILTIN_TASK_ENV\",\"_value\":\"\",\"_valueType\":\"string\"}"}],"_successful":false,"_projectName":"CanvasComponent-master","_moduleName":"entry","_taskName":"default@CollectDebugSymbol","_key":":CanvasComponent-master:entry:default@CollectDebugSymbol","_executionId":":CanvasComponent-master:entry:default@CollectDebugSymbol:1776761005803","_inputFiles":{"dataType":"Map","value":[["D:\\CanvasComponent-master\\CanvasComponent-master\\entry\\build\\default\\intermediates\\loader_out\\default\\ets\\sourceMaps.map",{"fileSnapShotHashValue":"a6299c0f5bb71ed93ecfc3d09476957805f6606c7ee39f3d6c4b781fc7231c01"}],["D:\\CanvasComponent-master\\CanvasComponent-master\\entry\\build\\default\\intermediates\\libs\\default",{"isDirectory":true,"fileSnapShotHashValue":""}]]},"_outputFiles":{"dataType":"Map","value":[["D:\\CanvasComponent-master\\CanvasComponent-master\\entry\\build\\default\\outputs\\default\\symbol",{"isDirectory":true,"fileSnapShotHashValue":""}]]}}}